Metadata-Version: 2.1
Name: tgdsmells
Version: 1.0.0
Summary: Helper classes for the Team Group Data Sharing Medium & Electronic Local Link System.
Home-page: https://github.com/L0laapk3/tgdsmells/
Author: Viliam Vadocz
Author-email: viliam.vadocz@gmail.com
License: MIT
Download-URL: https://github.com/ViliamVadocz/tmcp/archive/v_1_0_0.tar.gz
Keywords: RLBot,protocol
Platform: UNKNOWN
Classifier: Development Status :: 4 - Beta
Classifier: Intended Audience :: Developers
Classifier: Topic :: Software Development :: Build Tools
Classifier: License :: OSI Approved :: MIT License
Classifier: Programming Language :: Python :: 3
Classifier: Programming Language :: Python :: 3.7
Classifier: Programming Language :: Python :: 3.8
